dirty_equals/__init__.py
dirty_equals/_base.py
dirty_equals/_boolean.py
dirty_equals/_datetime.py
dirty_equals/_dict.py
dirty_equals/_inspection.py
dirty_equals/_numeric.py
dirty_equals/_other.py
dirty_equals/_sequence.py
dirty_equals/_strings.py
dirty_equals/_utils.py
dirty_equals/py.typed
dirty_equals/version.py
dirty_equals-0.10.0.dist-info/METADATA
dirty_equals-0.10.0.dist-info/WHEEL
dirty_equals-0.10.0.dist-info/licenses/LICENSE
dirty_equals-0.10.0.dist-info/RECORD
