Metadata-Version: 2.4
Name: dirty-equals
Version: 0.10.0
Summary: Doing dirty (but extremely useful) things with equals.
Project-URL: Homepage, https://github.com/samuelcolvin/dirty-equals
Project-URL: Documentation, https://dirty-equals.helpmanual.io
Project-URL: Funding, https://github.com/sponsors/samuelcolvin
Project-URL: Source, https://github.com/samuelcolvin/dirty-equals
Project-URL: Changelog, https://github.com/samuelcolvin/dirty-equals/releases
Author-email: Samuel Colvin <s@muelcolvin.com>
License-Expression: MIT
License-File: LICENSE
Classifier: Development Status :: 4 - Beta
Classifier: Environment :: Console
Classifier: Environment :: MacOS X
Classifier: Framework :: Pytest
Classifier: Intended Audience :: Developers
Classifier: Intended Audience :: Education
Classifier: Intended Audience :: Information Technology
Classifier: Intended Audience :: Science/Research
Classifier: Intended Audience :: System Administrators
Classifier: License :: OSI Approved :: MIT License
Classifier: Operating System :: POSIX :: Linux
Classifier: Operating System :: Unix
Classifier: Programming Language :: Python :: 3 :: Only
Classifier: Programming Language :: Python :: 3.9
Classifier: Programming Language :: Python :: 3.10
Classifier: Programming Language :: Python :: 3.11
Classifier: Programming Language :: Python :: 3.12
Classifier: Programming Language :: Python :: 3.13
Classifier: Topic :: Internet
Classifier: Topic :: Software Development :: Libraries :: Python Modules
Classifier: Typing :: Typed
Requires-Python: >=3.9
Provides-Extra: pydantic
Requires-Dist: pydantic>=2.4.2; extra == 'pydantic'
